{
  "40975ecf-68b1-49ec-8fc7-bd68fd4dde0e": {
    "gitAppName": "HI25",
    "lastCommitMessage": "H22",
    "gitVersionId": "5ac2b3e6-afc2-4ed9-816a-d424b9af2cef",
    "lastpushDate": "2025-02-19T20:29:29.579Z",
    "gitVersionName": "v1",
    "lastCommitUser": "aman "
  },
  "84d314af-7fdc-4701-8a54-282b69179e5d": {
    "gitAppName": "HI11",
    "lastCommitMessage": "tes2",
    "gitVersionId": "4a9aea5c-5720-4042-8454-ea4c2dc8fe81",
    "lastpushDate": "2025-02-19T20:32:22.386Z",
    "gitVersionName": "v1",
    "lastCommitUser": "aman "
  }
}